pretf_helpers/__init__.py
pretf_helpers/_log.py
pretf_helpers/aws.py
pretf_helpers/utils.py
pretf_helpers/workflow.py
pretf_helpers-0.2.8.dist-info/LICENSE
pretf_helpers-0.2.8.dist-info/METADATA
pretf_helpers-0.2.8.dist-info/WHEEL
pretf_helpers-0.2.8.dist-info/top_level.txt
pretf_helpers-0.2.8.dist-info/zip-safe
pretf_helpers-0.2.8.dist-info/RECORD
