Metadata-Version: 2.1
Name: pretf-helpers
Version: 0.2.8
Summary: Helper functions and classes for the pretf package
Home-page: https://gitlab.com/pepoluan/pretf_helpers
Author: Pandu POLUAN
Author-email: pepoluan@gmail.com
License: UNKNOWN
Project-URL: Bug Tracker, https://gitlab.com/pepoluan/pretf_helpers/-/issues
Project-URL: Source Code, https://gitlab.com/pepoluan/pretf_helpers/-/tree/master
Project-URL: Documentation, https://gitlab.com/pepoluan/pretf_helpers/-/wikis/home
Keywords: terraform pretf provisioning cloud
Platform: UNKNOWN
Classifier: Programming Language :: Python :: 3
Classifier: Development Status :: 4 - Beta
Classifier: Environment :: Console
Classifier: Intended Audience :: Developers
Classifier: Intended Audience :: System Administrators
Classifier: License :: OSI Approved :: Mozilla Public License 2.0 (MPL 2.0)
Classifier: Operating System :: OS Independent
Classifier: Topic :: Software Development :: Build Tools
Classifier: Topic :: System :: Installation/Setup
Classifier: Topic :: System :: Systems Administration
Requires-Python: >=3.6
Requires-Dist: pretf
Requires-Dist: pretf.aws
Requires-Dist: configparser
Requires-Dist: ruamel.yaml
